samatic/__init__.py
samatic/mood.py
samatic-1.0.0.dist-info/LICENSE
samatic-1.0.0.dist-info/METADATA
samatic-1.0.0.dist-info/WHEEL
samatic-1.0.0.dist-info/top_level.txt
samatic-1.0.0.dist-info/RECORD
