Metadata-Version: 2.1
Name: samatic
Version: 1.0.0
Summary: A fun console mood booster!
Home-page: UNKNOWN
Author: Sam
License: UNKNOWN
Platform: UNKNOWN
Requires-Python: >=3.7
